khloraascaf_utils/__init__.py
khloraascaf_utils/artificial_data.py
khloraascaf_utils/asm_graph_to_fasta.py
khloraascaf_utils/contigs_attributes.py
khloraascaf_utils/to_networkx.py
khloraascaf_utils-0.9.0.dist-info/LICENCE
khloraascaf_utils-0.9.0.dist-info/METADATA
khloraascaf_utils-0.9.0.dist-info/WHEEL
khloraascaf_utils-0.9.0.dist-info/top_level.txt
khloraascaf_utils-0.9.0.dist-info/RECORD
