Metadata-Version: 2.1
Name: khloraascaf-utils
Version: 0.9.0
Summary: Python utilities for khloraascaf python package.
Author-email: vepain <victor.epain@laposte.net>
License: ### GNU GENERAL PUBLIC LICENSE
Project-URL: Homepage, https://gitlab.com/khloraa_scaffolding/khloraascaf_utils
Project-URL: Repository, https://gitlab.com/khloraa_scaffolding/khloraascaf_utils
Project-URL: Documentation, https://khloraascaf-utils.readthedocs.io
Project-URL: Changelog, https://khloraascaf-utils.readthedocs.io/en/latest/changelog.html
Keywords: Scaffolding,Chloroplast,Assembly,DNA repeats
Classifier: Development Status :: 5 - Production/Stable
Classifier: Intended Audience :: Developers
Classifier: License :: OSI Approved :: GNU General Public License v3 or later (GPLv3+)
Classifier: Operating System :: Unix
Classifier: Programming Language :: Python :: 3.9
Classifier: Topic :: Software Development :: Libraries :: Python Modules
Requires-Python: >=3.9
License-File: LICENCE
Requires-Dist: khloraascaf (<1.11,>=1.10.0)
Requires-Dist: networkx (<3.1,>=3.0)
Requires-Dist: biopython (<1.82,>=1.81)
